npm_client
