Metadata-Version: 2.1
Name: npm_client
Version: 1.0.2
Summary: Python client for Nginx Proxy Manager
Home-page: https://github.com/ErilovNikita/npm-client
Author-email: minitwiks@gmail.com
License: MIT
License-File: LICENSE
Requires-Dist: requests==2.32.3
Requires-Dist: urllib3==2.2.3
Requires-Dist: pydantic==2.9.2
